algotrader/__init__.py
algotrader/main.py
algotrader/assets/assets_provider.py
algotrader/assets/correlation_config.json
algotrader/assets/crypto.symbols
algotrader/assets/sp500.symbols
algotrader/calc/__init__.py
algotrader/calc/calculations.py
algotrader/calc/technicals.py
algotrader/cli/__init__.py
algotrader/cli/helpers.py
algotrader/cli/main.py
algotrader/cli/pipeline.py
algotrader/cli/processors.py
algotrader/cli/sources.py
algotrader/cli/strategies.py
algotrader/entities/__init__.py
algotrader/entities/bucket.py
algotrader/entities/bucketscontainer.py
algotrader/entities/candle.py
algotrader/entities/candle_attachments.py
algotrader/entities/event.py
algotrader/entities/generic_candle_attachment.py
algotrader/entities/order_direction.py
algotrader/entities/serializable.py
algotrader/entities/strategy.py
algotrader/entities/strategy_signal.py
algotrader/entities/timespan.py
algotrader/examples/mongo-history-by-buckets.md
algotrader/examples/pipeline-templates/backtest_history_buckets_backtester.json
algotrader/examples/pipeline-templates/backtest_history_similarity_backtester.json
algotrader/examples/pipeline-templates/backtest_mongo_source_rsi_strategy.json
algotrader/examples/pipeline-templates/backtest_technicals_with_buckets_calculator.json
algotrader/examples/pipeline-templates/bins.json
algotrader/examples/pipeline-templates/build_daily_binance_loader.json
algotrader/examples/pipeline-templates/build_daily_yahoo_loader.json
algotrader/examples/pipeline-templates/build_realtime_binance.json
algotrader/examples/pipeline-templates/correlation.json
algotrader/examples/pipeline-templates/loader_simple_daily_loader.json
algotrader/examples/pipeline-templates/loader_simple_returns_calculator.json
algotrader/examples/pipeline-templates/loader_simple_technicals_calculator.json
algotrader/examples/pipeline-templates/loader_technicals_with_buckets_matcher.json
algotrader/logger/__init__.py
algotrader/market/__init__.py
algotrader/market/async_market_provider.py
algorithmic_trader-0.0.6.dist-info/LICENSE
algorithmic_trader-0.0.6.dist-info/METADATA
algorithmic_trader-0.0.6.dist-info/WHEEL
algorithmic_trader-0.0.6.dist-info/entry_points.txt
algorithmic_trader-0.0.6.dist-info/top_level.txt
algorithmic_trader-0.0.6.dist-info/RECORD
