Metadata-Version: 2.1
Name: algorithmic-trader
Version: 0.0.6
Summary: Trading bot with support for realtime trading, backtesting, custom strategies and much more
Author: Idan Yael
Maintainer: Idan Yael
License: MIT
Project-URL: homepage, https://github.com/idanya/algo-trader
Project-URL: repository, https://github.com/idanya/algo-trader
Project-URL: documentation, https://github.com/idanya/algo-trader/blob/main/README.md
Project-URL: bug-tracker, https://github.com/idanya/algo-trader/issues
Keywords: algo-trader,trading,backtesting,strategy,bot
Classifier: Programming Language :: Python :: 3
Classifier: Programming Language :: Python :: 3.10
Classifier: Operating System :: OS Independent
Requires-Python: >=3.10
License-File: LICENSE
Requires-Dist: newtulipy (==0.4.6)
Requires-Dist: pymongo (==3.12.0)
Requires-Dist: mongomock (==4.1.2)
Requires-Dist: scipy (==1.9.3)
Requires-Dist: yfinance (==0.1.87)
Requires-Dist: flake8 (==5.0.4)
Requires-Dist: typer[all] (==0.7.0)
Requires-Dist: coverage (==6.5.0)
Requires-Dist: binance-connector (==1.18.0)
Requires-Dist: python-dotenv (==0.21.0)
